AMRfior/AMRfior.py
AMRfior/AMRfior_Gene_Stats.py
AMRfior/AMRfior_Recompute.py
AMRfior/__init__.py
AMRfior/constants.py
AMRfior/databases.py
AMRfior/gene_stats.py
AMRfior/utils.py
AMRfior/workflow.py
AMRfior/databases/card/blast_aa/protein_fasta_protein_homolog_model_SID_blastdb.pdb
AMRfior/databases/card/blast_aa/protein_fasta_protein_homolog_model_SID_blastdb.phr
AMRfior/databases/card/blast_aa/protein_fasta_protein_homolog_model_SID_blastdb.pin
AMRfior/databases/card/blast_aa/protein_fasta_protein_homolog_model_SID_blastdb.pjs
AMRfior/databases/card/blast_aa/protein_fasta_protein_homolog_model_SID_blastdb.pot
AMRfior/databases/card/blast_aa/protein_fasta_protein_homolog_model_SID_blastdb.psq
AMRfior/databases/card/blast_aa/protein_fasta_protein_homolog_model_SID_blastdb.ptf
AMRfior/databases/card/blast_aa/protein_fasta_protein_homolog_model_SID_blastdb.pto
AMRfior/databases/card/blast_dna/nucleotide_fasta_protein_homolog_model_SID_blastdb.ndb
AMRfior/databases/card/blast_dna/nucleotide_fasta_protein_homolog_model_SID_blastdb.nhr
AMRfior/databases/card/blast_dna/nucleotide_fasta_protein_homolog_model_SID_blastdb.nin
AMRfior/databases/card/blast_dna/nucleotide_fasta_protein_homolog_model_SID_blastdb.njs
AMRfior/databases/card/blast_dna/nucleotide_fasta_protein_homolog_model_SID_blastdb.not
AMRfior/databases/card/blast_dna/nucleotide_fasta_protein_homolog_model_SID_blastdb.nsq
AMRfior/databases/card/blast_dna/nucleotide_fasta_protein_homolog_model_SID_blastdb.ntf
AMRfior/databases/card/blast_dna/nucleotide_fasta_protein_homolog_model_SID_blastdb.nto
AMRfior/databases/card/bowtie2/nucleotide_fasta_protein_homolog_model_SID_bowtie2db.1.bt2
AMRfior/databases/card/bowtie2/nucleotide_fasta_protein_homolog_model_SID_bowtie2db.2.bt2
AMRfior/databases/card/bowtie2/nucleotide_fasta_protein_homolog_model_SID_bowtie2db.3.bt2
AMRfior/databases/card/bowtie2/nucleotide_fasta_protein_homolog_model_SID_bowtie2db.4.bt2
amrfior-0.5.0.dist-info/licenses/LICENSE
amrfior-0.5.0.dist-info/METADATA
amrfior-0.5.0.dist-info/WHEEL
amrfior-0.5.0.dist-info/entry_points.txt
amrfior-0.5.0.dist-info/top_level.txt
amrfior-0.5.0.dist-info/RECORD
