Metadata-Version: 2.4
Name: AMRfior
Version: 0.5.0
Summary: AMRfior: A toolkit that uses BLAST, BWA, Bowtie2, DIAMOND, and Minimap2 to search DNA and protein sequences against AMR databases (DNA and AA) such as CARD/RGI and ResFinder.
Author-email: Nicholas Dimonaco <nicholas@dimonaco.co.uk>
License:                     GNU GENERAL PUBLIC LICENSE
Project-URL: Homepage, https://github.com/NickJD/AMRfior
Project-URL: Bug Tracker, https://github.com/NickJD/AMRfior/issues
Keywords: Antimicrobial Resistance,Sequence Searching
Classifier: Programming Language :: Python :: 3
Classifier: License :: OSI Approved :: GNU General Public License v3 (GPLv3)
Classifier: Operating System :: OS Independent
Requires-Python: >=3.10
License-File: LICENSE
Dynamic: license-file
